asgi_cors.py
asgi_cors-1.0.1.dist-info/LICENSE
asgi_cors-1.0.1.dist-info/METADATA
asgi_cors-1.0.1.dist-info/WHEEL
asgi_cors-1.0.1.dist-info/top_level.txt
asgi_cors-1.0.1.dist-info/RECORD
