Metadata-Version: 2.1
Name: asgi-cors
Version: 1.0.1
Summary: ASGI middleware for applying CORS headers to an ASGI application
Home-page: https://github.com/simonw/asgi-cors
Author: Simon Willison
License: Apache License, Version 2.0
License-File: LICENSE
Provides-Extra: test
Requires-Dist: pytest; extra == "test"
Requires-Dist: pytest-asyncio; extra == "test"
Requires-Dist: httpx; extra == "test"
